goonj/__init__.py
goonj/core.py
goonj/entities.py
goonj/exception.py
goonj/rule_engine.py
goonj/smart_alert.py
goonj/utils.py
goonj/version.py
goonj/channels/__init__.py
goonj/channels/base_channel.py
goonj/channels/constants.py
goonj/channels/email_channel.py
goonj/channels/slack_channel.py
goonj/channels/sms_channel.py
goonj/conf/__init__.py
goonj/conf/channel_settings.py
goonj/conf/configuration.py
goonj/conf/constants.py
goonj/conf/email_sms_settings.py
goonj/conf/error_config_setting.py
goonj/conf/source_setting.py
goonj-0.2.0.dist-info/DESCRIPTION.rst
goonj-0.2.0.dist-info/METADATA
goonj-0.2.0.dist-info/RECORD
goonj-0.2.0.dist-info/WHEEL
goonj-0.2.0.dist-info/metadata.json
goonj-0.2.0.dist-info/top_level.txt
