Metadata-Version: 2.0
Name: goonj
Version: 0.2.0
Summary: A python library to enable easy alerting services across multiple channels.
Home-page: UNKNOWN
Author: sohit kumar,bkp
Author-email: sohit.kumar@treebohotels.com,bibek.padhy@treebohotels.com
License: BSD
Platform: UNKNOWN
Requires-Dist: yml (==0.0.1)
Requires-Dist: request (==0.0.26)
Requires-Dist: PyYAML (==3.12)
Requires-Dist: requests (==2.18.4)
Requires-Dist: pre-commit (==1.7.0)
Requires-Dist: pre-commit-hooks (==1.2.3)
Requires-Dist: croniter (==0.3.5)
